odoo/addons/mail_suggested_recipient_unchecked/README.rst
odoo/addons/mail_suggested_recipient_unchecked/__init__.py
odoo/addons/mail_suggested_recipient_unchecked/__manifest__.py
odoo/addons/mail_suggested_recipient_unchecked/i18n/de.po
odoo/addons/mail_suggested_recipient_unchecked/i18n/it.po
odoo/addons/mail_suggested_recipient_unchecked/i18n/mail_suggested_recipient_unchecked.pot
odoo/addons/mail_suggested_recipient_unchecked/models/__init__.py
odoo/addons/mail_suggested_recipient_unchecked/models/mail_thread.py
odoo/addons/mail_suggested_recipient_unchecked/readme/CONTRIBUTORS.md
odoo/addons/mail_suggested_recipient_unchecked/readme/DESCRIPTION.md
odoo/addons/mail_suggested_recipient_unchecked/readme/USAGE.md
odoo/addons/mail_suggested_recipient_unchecked/static/description/icon.png
odoo/addons/mail_suggested_recipient_unchecked/static/description/index.html
odoo/addons/mail_suggested_recipient_unchecked/tests/__init__.py
odoo/addons/mail_suggested_recipient_unchecked/tests/test_mail_suggested_recipient_unchecked.py
odoo_addon_mail_suggested_recipient_unchecked-18.0.1.0.0.4.dist-info/METADATA
odoo_addon_mail_suggested_recipient_unchecked-18.0.1.0.0.4.dist-info/WHEEL
odoo_addon_mail_suggested_recipient_unchecked-18.0.1.0.0.4.dist-info/top_level.txt
odoo_addon_mail_suggested_recipient_unchecked-18.0.1.0.0.4.dist-info/RECORD
